numdoclinter/__init__.py
numdoclinter/actions.py
numdoclinter/linter.py
numdoclinter/parse.py
numdoclinter-0.1.0.dist-info/LICENSE
numdoclinter-0.1.0.dist-info/METADATA
numdoclinter-0.1.0.dist-info/WHEEL
numdoclinter-0.1.0.dist-info/entry_points.txt
numdoclinter-0.1.0.dist-info/top_level.txt
numdoclinter-0.1.0.dist-info/RECORD
