Metadata-Version: 2.1
Name: numdoclinter
Version: 0.1.0
Summary: UNKNOWN
Home-page: https://github.com/peterprescott/numdoclinter
Author: Peter Prescott
Author-email: prescott.peter@gmail.com
License: UNKNOWN
Project-URL: Bug Tracker, https://github.com/peterprescott/numdoclinter/issues
Platform: UNKNOWN
Requires-Python: >=3.6
License-File: LICENSE
Requires-Dist: pandas
Requires-Dist: sphinx
Requires-Dist: fire
